README.rst
setup.py
pull_into_place/__init__.py
pull_into_place/big_jobs.py
pull_into_place/main.py
pull_into_place/pipeline.py
pull_into_place/structures.py
pull_into_place.egg-info/PKG-INFO
pull_into_place.egg-info/SOURCES.txt
pull_into_place.egg-info/dependency_links.txt
pull_into_place.egg-info/entry_points.txt
pull_into_place.egg-info/requires.txt
pull_into_place.egg-info/top_level.txt
pull_into_place/big_jobs/build_models.xml
pull_into_place/big_jobs/design_models.xml
pull_into_place/big_jobs/pip_build.py
pull_into_place/big_jobs/pip_design.py
pull_into_place/big_jobs/pip_validate.py
pull_into_place/big_jobs/shared_defs.xml
pull_into_place/big_jobs/validate_designs.xml
pull_into_place/commands/01_setup_workspace.py
pull_into_place/commands/02_setup_model_fragments.py
pull_into_place/commands/03_build_models.py
pull_into_place/commands/04_pick_models_to_design.py
pull_into_place/commands/05_design_models.py
pull_into_place/commands/06_manually_pick_designs_to_validate.py
pull_into_place/commands/06_pick_designs_to_validate.py
pull_into_place/commands/07_setup_design_fragments.py
pull_into_place/commands/08_validate_designs.py
pull_into_place/commands/09_compare_best_designs.py
pull_into_place/commands/__init__.py
pull_into_place/commands/cache_models.py
pull_into_place/commands/count_models.py
pull_into_place/commands/fetch_and_cache_models.py
pull_into_place/commands/fetch_data.py
pull_into_place/commands/make_web_logo.py
pull_into_place/commands/plot_funnels.py
pull_into_place/commands/push_data.py