Metadata-Version: 1.1
Name: pull-into-place
Version: 1.0.1
Summary: A rosetta pipeline to position important protein sidechains with sub-angstrom accuracy.
Home-page: https://github.com/Kortemme-Lab/pull_into_place
Author: Kale Kundert
Author-email: kale.kundert@ucsf.edu
License: GPLv3
Download-URL: https://github.com/Kortemme-Lab/pull_into_place/tarball/v1.0.1
Keywords: scientific,rosetta,design,protein,sidechain
Platform: UNKNOWN
Classifier: Development Status :: 2 - Pre-Alpha
Classifier: Intended Audience :: Science/Research
Classifier: License :: OSI Approved :: GNU General Public License v3 (GPLv3)
Classifier: Natural Language :: English
Classifier: Programming Language :: Python :: 2
Classifier: Topic :: Scientific/Engineering :: Bio-Informatics
